src/__init__.py
src/app.py
src/cli.py
src/reporter.py
src/attacks/__init__.py
src/attacks/context_override.py
src/attacks/data_exfil.py
src/attacks/dos.py
src/attacks/goal_hijack.py
src/attacks/injection.py
src/attacks/jailbreak.py
src/attacks/memory_poison.py
src/attacks/multi_turn.py
src/attacks/payloads.py
src/attacks/privilege_escalation.py
src/attacks/tool_abuse.py
src/classifier/__init__.py
src/classifier/cli.py
src/classifier/dataset.py
src/classifier/inference.py
src/classifier/train.py
src/core/__init__.py
src/core/adapters.py
src/core/attack.py
src/core/config.py
src/core/scoring.py
src/core/target.py
src/dashboard/__init__.py
src/dashboard/app.py
src/defense/__init__.py
src/defense/classifier.py
src/defense/policy.py
src/defense/rules.py
src/reporter/__init__.py
src/reporter/quick_report.py
src/sandbox/sandbox.py
veritas_redteam-1.0.0.dist-info/licenses/LICENSE
veritas_redteam-1.0.0.dist-info/METADATA
veritas_redteam-1.0.0.dist-info/WHEEL
veritas_redteam-1.0.0.dist-info/entry_points.txt
veritas_redteam-1.0.0.dist-info/top_level.txt
veritas_redteam-1.0.0.dist-info/RECORD
