Metadata-Version: 2.4
Name: veritas-redteam
Version: 1.0.0
Summary: Automated Red Teaming Suite for AI Agents - 'Burp Suite for AI'
Author: Aryan Thakur
License: MIT
Project-URL: Homepage, https://github.com/ARYAN2302/veritas
Project-URL: Documentation, https://github.com/ARYAN2302/veritas#readme
Project-URL: Repository, https://github.com/ARYAN2302/veritas
Project-URL: Issues, https://github.com/ARYAN2302/veritas/issues
Keywords: ai-safety,red-teaming,llm-security,prompt-injection,jailbreak,agent-security
Classifier: Development Status :: 4 - Beta
Classifier: Intended Audience :: Developers
Classifier: Intended Audience :: Science/Research
Classifier: License :: OSI Approved :: MIT License
Classifier: Operating System :: OS Independent
Classifier: Programming Language :: Python :: 3
Classifier: Programming Language :: Python :: 3.10
Classifier: Programming Language :: Python :: 3.11
Classifier: Programming Language :: Python :: 3.12
Classifier: Topic :: Security
Classifier: Topic :: Scientific/Engineering :: Artificial Intelligence
Requires-Python: >=3.10
License-File: LICENSE
Requires-Dist: pyyaml>=6.0
Requires-Dist: rich>=13.0
Provides-Extra: full
Requires-Dist: docker>=7.0; extra == "full"
Requires-Dist: reportlab>=4.0; extra == "full"
Requires-Dist: langchain-groq>=0.1; extra == "full"
Requires-Dist: langchain-core>=0.1; extra == "full"
Requires-Dist: streamlit>=1.28; extra == "full"
Requires-Dist: transformers>=4.35; extra == "full"
Requires-Dist: torch>=2.0; extra == "full"
Requires-Dist: scikit-learn>=1.3; extra == "full"
Provides-Extra: classifier
Requires-Dist: transformers>=4.35; extra == "classifier"
Requires-Dist: torch>=2.0; extra == "classifier"
Requires-Dist: scikit-learn>=1.3; extra == "classifier"
Requires-Dist: accelerate>=0.24; extra == "classifier"
Provides-Extra: dev
Requires-Dist: pytest>=7.0; extra == "dev"
Requires-Dist: pytest-cov>=4.0; extra == "dev"
Requires-Dist: ruff>=0.1; extra == "dev"
Requires-Dist: mypy>=1.0; extra == "dev"
Requires-Dist: build>=1.0; extra == "dev"
Requires-Dist: twine>=4.0; extra == "dev"
Provides-Extra: openai
Requires-Dist: openai>=1.0; extra == "openai"
Provides-Extra: anthropic
Requires-Dist: anthropic>=0.18; extra == "anthropic"
Dynamic: license-file
